{"binary_error": 0.21800092194222495, "time_this_iter_s": 12.435277223587036, "done": false, "timesteps_total": null, "episodes_total": null, "training_iteration": 1, "experiment_id": "869f30e345a040409cc5f7276756e710", "date": "2021-03-18_15-46-02", "timestamp": 1616082362, "time_total_s": 12.435277223587036, "pid": 36557, "hostname": "MacBook-Pro-3", "node_ip": "192.168.0.4", "config": {"objective": "binary", "metric": "binary_error", "mode": "max", "verbose": -1, "boosting_type": "dart", "num_leaves": 11, "learning_rate": 0.06681927520553171}, "time_since_restore": 12.435277223587036, "timesteps_since_restore": 0, "iterations_since_restore": 1, "trial_id": "fe4c4_00003"}
{"binary_error": 0.21800092194222495, "time_this_iter_s": 0.12531566619873047, "done": false, "timesteps_total": null, "episodes_total": null, "training_iteration": 2, "experiment_id": "869f30e345a040409cc5f7276756e710", "date": "2021-03-18_15-46-02", "timestamp": 1616082362, "time_total_s": 12.560592889785767, "pid": 36557, "hostname": "MacBook-Pro-3", "node_ip": "192.168.0.4", "config": {"objective": "binary", "metric": "binary_error", "mode": "max", "verbose": -1, "boosting_type": "dart", "num_leaves": 11, "learning_rate": 0.06681927520553171}, "time_since_restore": 12.560592889785767, "timesteps_since_restore": 0, "iterations_since_restore": 2, "trial_id": "fe4c4_00003"}
{"binary_error": 0.21800092194222495, "time_this_iter_s": 0.11348915100097656, "done": false, "timesteps_total": null, "episodes_total": null, "training_iteration": 3, "experiment_id": "869f30e345a040409cc5f7276756e710", "date": "2021-03-18_15-46-02", "timestamp": 1616082362, "time_total_s": 12.674082040786743, "pid": 36557, "hostname": "MacBook-Pro-3", "node_ip": "192.168.0.4", "config": {"objective": "binary", "metric": "binary_error", "mode": "max", "verbose": -1, "boosting_type": "dart", "num_leaves": 11, "learning_rate": 0.06681927520553171}, "time_since_restore": 12.674082040786743, "timesteps_since_restore": 0, "iterations_since_restore": 3, "trial_id": "fe4c4_00003"}
{"binary_error": 0.21800092194222495, "time_this_iter_s": 0.11730694770812988, "done": false, "timesteps_total": null, "episodes_total": null, "training_iteration": 4, "experiment_id": "869f30e345a040409cc5f7276756e710", "date": "2021-03-18_15-46-02", "timestamp": 1616082362, "time_total_s": 12.791388988494873, "pid": 36557, "hostname": "MacBook-Pro-3", "node_ip": "192.168.0.4", "config": {"objective": "binary", "metric": "binary_error", "mode": "max", "verbose": -1, "boosting_type": "dart", "num_leaves": 11, "learning_rate": 0.06681927520553171}, "time_since_restore": 12.791388988494873, "timesteps_since_restore": 0, "iterations_since_restore": 4, "trial_id": "fe4c4_00003"}
{"binary_error": 0.21800092194222495, "time_this_iter_s": 0.11968994140625, "done": false, "timesteps_total": null, "episodes_total": null, "training_iteration": 5, "experiment_id": "869f30e345a040409cc5f7276756e710", "date": "2021-03-18_15-46-02", "timestamp": 1616082362, "time_total_s": 12.911078929901123, "pid": 36557, "hostname": "MacBook-Pro-3", "node_ip": "192.168.0.4", "config": {"objective": "binary", "metric": "binary_error", "mode": "max", "verbose": -1, "boosting_type": "dart", "num_leaves": 11, "learning_rate": 0.06681927520553171}, "time_since_restore": 12.911078929901123, "timesteps_since_restore": 0, "iterations_since_restore": 5, "trial_id": "fe4c4_00003"}
{"binary_error": 0.21800092194222495, "time_this_iter_s": 0.12025594711303711, "done": false, "timesteps_total": null, "episodes_total": null, "training_iteration": 6, "experiment_id": "869f30e345a040409cc5f7276756e710", "date": "2021-03-18_15-46-02", "timestamp": 1616082362, "time_total_s": 13.03133487701416, "pid": 36557, "hostname": "MacBook-Pro-3", "node_ip": "192.168.0.4", "config": {"objective": "binary", "metric": "binary_error", "mode": "max", "verbose": -1, "boosting_type": "dart", "num_leaves": 11, "learning_rate": 0.06681927520553171}, "time_since_restore": 13.03133487701416, "timesteps_since_restore": 0, "iterations_since_restore": 6, "trial_id": "fe4c4_00003"}
{"binary_error": 0.21800092194222495, "time_this_iter_s": 0.12418627738952637, "done": false, "timesteps_total": null, "episodes_total": null, "training_iteration": 7, "experiment_id": "869f30e345a040409cc5f7276756e710", "date": "2021-03-18_15-46-02", "timestamp": 1616082362, "time_total_s": 13.155521154403687, "pid": 36557, "hostname": "MacBook-Pro-3", "node_ip": "192.168.0.4", "config": {"objective": "binary", "metric": "binary_error", "mode": "max", "verbose": -1, "boosting_type": "dart", "num_leaves": 11, "learning_rate": 0.06681927520553171}, "time_since_restore": 13.155521154403687, "timesteps_since_restore": 0, "iterations_since_restore": 7, "trial_id": "fe4c4_00003"}
{"binary_error": 0.21800092194222495, "time_this_iter_s": 0.14401674270629883, "done": false, "timesteps_total": null, "episodes_total": null, "training_iteration": 8, "experiment_id": "869f30e345a040409cc5f7276756e710", "date": "2021-03-18_15-46-02", "timestamp": 1616082362, "time_total_s": 13.299537897109985, "pid": 36557, "hostname": "MacBook-Pro-3", "node_ip": "192.168.0.4", "config": {"objective": "binary", "metric": "binary_error", "mode": "max", "verbose": -1, "boosting_type": "dart", "num_leaves": 11, "learning_rate": 0.06681927520553171}, "time_since_restore": 13.299537897109985, "timesteps_since_restore": 0, "iterations_since_restore": 8, "trial_id": "fe4c4_00003"}
{"binary_error": 0.21800092194222495, "time_this_iter_s": 0.11891937255859375, "done": false, "timesteps_total": null, "episodes_total": null, "training_iteration": 9, "experiment_id": "869f30e345a040409cc5f7276756e710", "date": "2021-03-18_15-46-03", "timestamp": 1616082363, "time_total_s": 13.418457269668579, "pid": 36557, "hostname": "MacBook-Pro-3", "node_ip": "192.168.0.4", "config": {"objective": "binary", "metric": "binary_error", "mode": "max", "verbose": -1, "boosting_type": "dart", "num_leaves": 11, "learning_rate": 0.06681927520553171}, "time_since_restore": 13.418457269668579, "timesteps_since_restore": 0, "iterations_since_restore": 9, "trial_id": "fe4c4_00003"}
{"binary_error": 0.21800092194222495, "time_this_iter_s": 0.12214183807373047, "done": false, "timesteps_total": null, "episodes_total": null, "training_iteration": 10, "experiment_id": "869f30e345a040409cc5f7276756e710", "date": "2021-03-18_15-46-03", "timestamp": 1616082363, "time_total_s": 13.54059910774231, "pid": 36557, "hostname": "MacBook-Pro-3", "node_ip": "192.168.0.4", "config": {"objective": "binary", "metric": "binary_error", "mode": "max", "verbose": -1, "boosting_type": "dart", "num_leaves": 11, "learning_rate": 0.06681927520553171}, "time_since_restore": 13.54059910774231, "timesteps_since_restore": 0, "iterations_since_restore": 10, "trial_id": "fe4c4_00003"}
{"binary_error": 0.21800092194222495, "time_this_iter_s": 0.12542200088500977, "done": false, "timesteps_total": null, "episodes_total": null, "training_iteration": 11, "experiment_id": "869f30e345a040409cc5f7276756e710", "date": "2021-03-18_15-46-03", "timestamp": 1616082363, "time_total_s": 13.66602110862732, "pid": 36557, "hostname": "MacBook-Pro-3", "node_ip": "192.168.0.4", "config": {"objective": "binary", "metric": "binary_error", "mode": "max", "verbose": -1, "boosting_type": "dart", "num_leaves": 11, "learning_rate": 0.06681927520553171}, "time_since_restore": 13.66602110862732, "timesteps_since_restore": 0, "iterations_since_restore": 11, "trial_id": "fe4c4_00003"}
{"binary_error": 0.21800092194222495, "time_this_iter_s": 0.14839887619018555, "done": false, "timesteps_total": null, "episodes_total": null, "training_iteration": 12, "experiment_id": "869f30e345a040409cc5f7276756e710", "date": "2021-03-18_15-46-03", "timestamp": 1616082363, "time_total_s": 13.814419984817505, "pid": 36557, "hostname": "MacBook-Pro-3", "node_ip": "192.168.0.4", "config": {"objective": "binary", "metric": "binary_error", "mode": "max", "verbose": -1, "boosting_type": "dart", "num_leaves": 11, "learning_rate": 0.06681927520553171}, "time_since_restore": 13.814419984817505, "timesteps_since_restore": 0, "iterations_since_restore": 12, "trial_id": "fe4c4_00003"}
{"binary_error": 0.21800092194222495, "time_this_iter_s": 0.1208791732788086, "done": false, "timesteps_total": null, "episodes_total": null, "training_iteration": 13, "experiment_id": "869f30e345a040409cc5f7276756e710", "date": "2021-03-18_15-46-03", "timestamp": 1616082363, "time_total_s": 13.935299158096313, "pid": 36557, "hostname": "MacBook-Pro-3", "node_ip": "192.168.0.4", "config": {"objective": "binary", "metric": "binary_error", "mode": "max", "verbose": -1, "boosting_type": "dart", "num_leaves": 11, "learning_rate": 0.06681927520553171}, "time_since_restore": 13.935299158096313, "timesteps_since_restore": 0, "iterations_since_restore": 13, "trial_id": "fe4c4_00003"}
{"binary_error": 0.21800092194222495, "time_this_iter_s": 0.1209568977355957, "done": false, "timesteps_total": null, "episodes_total": null, "training_iteration": 14, "experiment_id": "869f30e345a040409cc5f7276756e710", "date": "2021-03-18_15-46-03", "timestamp": 1616082363, "time_total_s": 14.05625605583191, "pid": 36557, "hostname": "MacBook-Pro-3", "node_ip": "192.168.0.4", "config": {"objective": "binary", "metric": "binary_error", "mode": "max", "verbose": -1, "boosting_type": "dart", "num_leaves": 11, "learning_rate": 0.06681927520553171}, "time_since_restore": 14.05625605583191, "timesteps_since_restore": 0, "iterations_since_restore": 14, "trial_id": "fe4c4_00003"}
{"binary_error": 0.21800092194222495, "time_this_iter_s": 0.12715601921081543, "done": false, "timesteps_total": null, "episodes_total": null, "training_iteration": 15, "experiment_id": "869f30e345a040409cc5f7276756e710", "date": "2021-03-18_15-46-03", "timestamp": 1616082363, "time_total_s": 14.183412075042725, "pid": 36557, "hostname": "MacBook-Pro-3", "node_ip": "192.168.0.4", "config": {"objective": "binary", "metric": "binary_error", "mode": "max", "verbose": -1, "boosting_type": "dart", "num_leaves": 11, "learning_rate": 0.06681927520553171}, "time_since_restore": 14.183412075042725, "timesteps_since_restore": 0, "iterations_since_restore": 15, "trial_id": "fe4c4_00003"}
{"binary_error": 0.21800092194222495, "time_this_iter_s": 0.12098193168640137, "done": false, "timesteps_total": null, "episodes_total": null, "training_iteration": 16, "experiment_id": "869f30e345a040409cc5f7276756e710", "date": "2021-03-18_15-46-03", "timestamp": 1616082363, "time_total_s": 14.304394006729126, "pid": 36557, "hostname": "MacBook-Pro-3", "node_ip": "192.168.0.4", "config": {"objective": "binary", "metric": "binary_error", "mode": "max", "verbose": -1, "boosting_type": "dart", "num_leaves": 11, "learning_rate": 0.06681927520553171}, "time_since_restore": 14.304394006729126, "timesteps_since_restore": 0, "iterations_since_restore": 16, "trial_id": "fe4c4_00003"}
{"binary_error": 0.21800092194222495, "time_this_iter_s": 0.1256861686706543, "done": false, "timesteps_total": null, "episodes_total": null, "training_iteration": 17, "experiment_id": "869f30e345a040409cc5f7276756e710", "date": "2021-03-18_15-46-04", "timestamp": 1616082364, "time_total_s": 14.43008017539978, "pid": 36557, "hostname": "MacBook-Pro-3", "node_ip": "192.168.0.4", "config": {"objective": "binary", "metric": "binary_error", "mode": "max", "verbose": -1, "boosting_type": "dart", "num_leaves": 11, "learning_rate": 0.06681927520553171}, "time_since_restore": 14.43008017539978, "timesteps_since_restore": 0, "iterations_since_restore": 17, "trial_id": "fe4c4_00003"}
{"binary_error": 0.20559311616472034, "time_this_iter_s": 0.12723398208618164, "done": false, "timesteps_total": null, "episodes_total": null, "training_iteration": 18, "experiment_id": "869f30e345a040409cc5f7276756e710", "date": "2021-03-18_15-46-04", "timestamp": 1616082364, "time_total_s": 14.557314157485962, "pid": 36557, "hostname": "MacBook-Pro-3", "node_ip": "192.168.0.4", "config": {"objective": "binary", "metric": "binary_error", "mode": "max", "verbose": -1, "boosting_type": "dart", "num_leaves": 11, "learning_rate": 0.06681927520553171}, "time_since_restore": 14.557314157485962, "timesteps_since_restore": 0, "iterations_since_restore": 18, "trial_id": "fe4c4_00003"}
{"binary_error": 0.20267363245236633, "time_this_iter_s": 0.11567473411560059, "done": false, "timesteps_total": null, "episodes_total": null, "training_iteration": 19, "experiment_id": "869f30e345a040409cc5f7276756e710", "date": "2021-03-18_15-46-04", "timestamp": 1616082364, "time_total_s": 14.672988891601562, "pid": 36557, "hostname": "MacBook-Pro-3", "node_ip": "192.168.0.4", "config": {"objective": "binary", "metric": "binary_error", "mode": "max", "verbose": -1, "boosting_type": "dart", "num_leaves": 11, "learning_rate": 0.06681927520553171}, "time_since_restore": 14.672988891601562, "timesteps_since_restore": 0, "iterations_since_restore": 19, "trial_id": "fe4c4_00003"}
{"binary_error": 0.1991779348494161, "time_this_iter_s": 0.1230320930480957, "done": false, "timesteps_total": null, "episodes_total": null, "training_iteration": 20, "experiment_id": "869f30e345a040409cc5f7276756e710", "date": "2021-03-18_15-46-04", "timestamp": 1616082364, "time_total_s": 14.796020984649658, "pid": 36557, "hostname": "MacBook-Pro-3", "node_ip": "192.168.0.4", "config": {"objective": "binary", "metric": "binary_error", "mode": "max", "verbose": -1, "boosting_type": "dart", "num_leaves": 11, "learning_rate": 0.06681927520553171}, "time_since_restore": 14.796020984649658, "timesteps_since_restore": 0, "iterations_since_restore": 20, "trial_id": "fe4c4_00003"}
{"binary_error": 0.20113706207744314, "time_this_iter_s": 0.14115405082702637, "done": false, "timesteps_total": null, "episodes_total": null, "training_iteration": 21, "experiment_id": "869f30e345a040409cc5f7276756e710", "date": "2021-03-18_15-46-04", "timestamp": 1616082364, "time_total_s": 14.937175035476685, "pid": 36557, "hostname": "MacBook-Pro-3", "node_ip": "192.168.0.4", "config": {"objective": "binary", "metric": "binary_error", "mode": "max", "verbose": -1, "boosting_type": "dart", "num_leaves": 11, "learning_rate": 0.06681927520553171}, "time_since_restore": 14.937175035476685, "timesteps_since_restore": 0, "iterations_since_restore": 21, "trial_id": "fe4c4_00003"}
{"binary_error": 0.19852489244007376, "time_this_iter_s": 0.11512088775634766, "done": false, "timesteps_total": null, "episodes_total": null, "training_iteration": 22, "experiment_id": "869f30e345a040409cc5f7276756e710", "date": "2021-03-18_15-46-04", "timestamp": 1616082364, "time_total_s": 15.052295923233032, "pid": 36557, "hostname": "MacBook-Pro-3", "node_ip": "192.168.0.4", "config": {"objective": "binary", "metric": "binary_error", "mode": "max", "verbose": -1, "boosting_type": "dart", "num_leaves": 11, "learning_rate": 0.06681927520553171}, "time_since_restore": 15.052295923233032, "timesteps_since_restore": 0, "iterations_since_restore": 22, "trial_id": "fe4c4_00003"}
{"binary_error": 0.19702673632452367, "time_this_iter_s": 0.11571002006530762, "done": false, "timesteps_total": null, "episodes_total": null, "training_iteration": 23, "experiment_id": "869f30e345a040409cc5f7276756e710", "date": "2021-03-18_15-46-04", "timestamp": 1616082364, "time_total_s": 15.16800594329834, "pid": 36557, "hostname": "MacBook-Pro-3", "node_ip": "192.168.0.4", "config": {"objective": "binary", "metric": "binary_error", "mode": "max", "verbose": -1, "boosting_type": "dart", "num_leaves": 11, "learning_rate": 0.06681927520553171}, "time_since_restore": 15.16800594329834, "timesteps_since_restore": 0, "iterations_since_restore": 23, "trial_id": "fe4c4_00003"}
{"binary_error": 0.19464505224339274, "time_this_iter_s": 0.11375308036804199, "done": false, "timesteps_total": null, "episodes_total": null, "training_iteration": 24, "experiment_id": "869f30e345a040409cc5f7276756e710", "date": "2021-03-18_15-46-04", "timestamp": 1616082364, "time_total_s": 15.281759023666382, "pid": 36557, "hostname": "MacBook-Pro-3", "node_ip": "192.168.0.4", "config": {"objective": "binary", "metric": "binary_error", "mode": "max", "verbose": -1, "boosting_type": "dart", "num_leaves": 11, "learning_rate": 0.06681927520553171}, "time_since_restore": 15.281759023666382, "timesteps_since_restore": 0, "iterations_since_restore": 24, "trial_id": "fe4c4_00003"}
{"binary_error": 0.19226336816226183, "time_this_iter_s": 0.11874008178710938, "done": false, "timesteps_total": null, "episodes_total": null, "training_iteration": 25, "experiment_id": "869f30e345a040409cc5f7276756e710", "date": "2021-03-18_15-46-05", "timestamp": 1616082365, "time_total_s": 15.400499105453491, "pid": 36557, "hostname": "MacBook-Pro-3", "node_ip": "192.168.0.4", "config": {"objective": "binary", "metric": "binary_error", "mode": "max", "verbose": -1, "boosting_type": "dart", "num_leaves": 11, "learning_rate": 0.06681927520553171}, "time_since_restore": 15.400499105453491, "timesteps_since_restore": 0, "iterations_since_restore": 25, "trial_id": "fe4c4_00003"}
{"binary_error": 0.1915719114935464, "time_this_iter_s": 0.11784911155700684, "done": false, "timesteps_total": null, "episodes_total": null, "training_iteration": 26, "experiment_id": "869f30e345a040409cc5f7276756e710", "date": "2021-03-18_15-46-05", "timestamp": 1616082365, "time_total_s": 15.518348217010498, "pid": 36557, "hostname": "MacBook-Pro-3", "node_ip": "192.168.0.4", "config": {"objective": "binary", "metric": "binary_error", "mode": "max", "verbose": -1, "boosting_type": "dart", "num_leaves": 11, "learning_rate": 0.06681927520553171}, "time_since_restore": 15.518348217010498, "timesteps_since_restore": 0, "iterations_since_restore": 26, "trial_id": "fe4c4_00003"}
{"binary_error": 0.1903042409342348, "time_this_iter_s": 0.12292766571044922, "done": false, "timesteps_total": null, "episodes_total": null, "training_iteration": 27, "experiment_id": "869f30e345a040409cc5f7276756e710", "date": "2021-03-18_15-46-05", "timestamp": 1616082365, "time_total_s": 15.641275882720947, "pid": 36557, "hostname": "MacBook-Pro-3", "node_ip": "192.168.0.4", "config": {"objective": "binary", "metric": "binary_error", "mode": "max", "verbose": -1, "boosting_type": "dart", "num_leaves": 11, "learning_rate": 0.06681927520553171}, "time_since_restore": 15.641275882720947, "timesteps_since_restore": 0, "iterations_since_restore": 27, "trial_id": "fe4c4_00003"}
{"binary_error": 0.19057314074984635, "time_this_iter_s": 0.15950918197631836, "done": false, "timesteps_total": null, "episodes_total": null, "training_iteration": 28, "experiment_id": "869f30e345a040409cc5f7276756e710", "date": "2021-03-18_15-46-05", "timestamp": 1616082365, "time_total_s": 15.800785064697266, "pid": 36557, "hostname": "MacBook-Pro-3", "node_ip": "192.168.0.4", "config": {"objective": "binary", "metric": "binary_error", "mode": "max", "verbose": -1, "boosting_type": "dart", "num_leaves": 11, "learning_rate": 0.06681927520553171}, "time_since_restore": 15.800785064697266, "timesteps_since_restore": 0, "iterations_since_restore": 28, "trial_id": "fe4c4_00003"}
{"binary_error": 0.18957437000614627, "time_this_iter_s": 0.12897610664367676, "done": false, "timesteps_total": null, "episodes_total": null, "training_iteration": 29, "experiment_id": "869f30e345a040409cc5f7276756e710", "date": "2021-03-18_15-46-05", "timestamp": 1616082365, "time_total_s": 15.929761171340942, "pid": 36557, "hostname": "MacBook-Pro-3", "node_ip": "192.168.0.4", "config": {"objective": "binary", "metric": "binary_error", "mode": "max", "verbose": -1, "boosting_type": "dart", "num_leaves": 11, "learning_rate": 0.06681927520553171}, "time_since_restore": 15.929761171340942, "timesteps_since_restore": 0, "iterations_since_restore": 29, "trial_id": "fe4c4_00003"}
{"binary_error": 0.1884219422249539, "time_this_iter_s": 0.13398075103759766, "done": false, "timesteps_total": null, "episodes_total": null, "training_iteration": 30, "experiment_id": "869f30e345a040409cc5f7276756e710", "date": "2021-03-18_15-46-05", "timestamp": 1616082365, "time_total_s": 16.06374192237854, "pid": 36557, "hostname": "MacBook-Pro-3", "node_ip": "192.168.0.4", "config": {"objective": "binary", "metric": "binary_error", "mode": "max", "verbose": -1, "boosting_type": "dart", "num_leaves": 11, "learning_rate": 0.06681927520553171}, "time_since_restore": 16.06374192237854, "timesteps_since_restore": 0, "iterations_since_restore": 30, "trial_id": "fe4c4_00003"}
{"binary_error": 0.18884449907805778, "time_this_iter_s": 0.12787222862243652, "done": false, "timesteps_total": null, "episodes_total": null, "training_iteration": 31, "experiment_id": "869f30e345a040409cc5f7276756e710", "date": "2021-03-18_15-46-05", "timestamp": 1616082365, "time_total_s": 16.191614151000977, "pid": 36557, "hostname": "MacBook-Pro-3", "node_ip": "192.168.0.4", "config": {"objective": "binary", "metric": "binary_error", "mode": "max", "verbose": -1, "boosting_type": "dart", "num_leaves": 11, "learning_rate": 0.06681927520553171}, "time_since_restore": 16.191614151000977, "timesteps_since_restore": 0, "iterations_since_restore": 31, "trial_id": "fe4c4_00003"}
{"binary_error": 0.18796097111247695, "time_this_iter_s": 0.11333084106445312, "done": false, "timesteps_total": null, "episodes_total": null, "training_iteration": 32, "experiment_id": "869f30e345a040409cc5f7276756e710", "date": "2021-03-18_15-46-05", "timestamp": 1616082365, "time_total_s": 16.30494499206543, "pid": 36557, "hostname": "MacBook-Pro-3", "node_ip": "192.168.0.4", "config": {"objective": "binary", "metric": "binary_error", "mode": "max", "verbose": -1, "boosting_type": "dart", "num_leaves": 11, "learning_rate": 0.06681927520553171}, "time_since_restore": 16.30494499206543, "timesteps_since_restore": 0, "iterations_since_restore": 32, "trial_id": "fe4c4_00003"}
{"binary_error": 0.18688537185003073, "time_this_iter_s": 0.11730504035949707, "done": false, "timesteps_total": null, "episodes_total": null, "training_iteration": 33, "experiment_id": "869f30e345a040409cc5f7276756e710", "date": "2021-03-18_15-46-06", "timestamp": 1616082366, "time_total_s": 16.422250032424927, "pid": 36557, "hostname": "MacBook-Pro-3", "node_ip": "192.168.0.4", "config": {"objective": "binary", "metric": "binary_error", "mode": "max", "verbose": -1, "boosting_type": "dart", "num_leaves": 11, "learning_rate": 0.06681927520553171}, "time_since_restore": 16.422250032424927, "timesteps_since_restore": 0, "iterations_since_restore": 33, "trial_id": "fe4c4_00003"}
{"binary_error": 0.18627074370006147, "time_this_iter_s": 0.13387227058410645, "done": false, "timesteps_total": null, "episodes_total": null, "training_iteration": 34, "experiment_id": "869f30e345a040409cc5f7276756e710", "date": "2021-03-18_15-46-06", "timestamp": 1616082366, "time_total_s": 16.556122303009033, "pid": 36557, "hostname": "MacBook-Pro-3", "node_ip": "192.168.0.4", "config": {"objective": "binary", "metric": "binary_error", "mode": "max", "verbose": -1, "boosting_type": "dart", "num_leaves": 11, "learning_rate": 0.06681927520553171}, "time_since_restore": 16.556122303009033, "timesteps_since_restore": 0, "iterations_since_restore": 34, "trial_id": "fe4c4_00003"}
{"binary_error": 0.18677012907191148, "time_this_iter_s": 0.17640972137451172, "done": false, "timesteps_total": null, "episodes_total": null, "training_iteration": 35, "experiment_id": "869f30e345a040409cc5f7276756e710", "date": "2021-03-18_15-46-06", "timestamp": 1616082366, "time_total_s": 16.732532024383545, "pid": 36557, "hostname": "MacBook-Pro-3", "node_ip": "192.168.0.4", "config": {"objective": "binary", "metric": "binary_error", "mode": "max", "verbose": -1, "boosting_type": "dart", "num_leaves": 11, "learning_rate": 0.06681927520553171}, "time_since_restore": 16.732532024383545, "timesteps_since_restore": 0, "iterations_since_restore": 35, "trial_id": "fe4c4_00003"}
{"binary_error": 0.18773048555623847, "time_this_iter_s": 0.18346905708312988, "done": false, "timesteps_total": null, "episodes_total": null, "training_iteration": 36, "experiment_id": "869f30e345a040409cc5f7276756e710", "date": "2021-03-18_15-46-06", "timestamp": 1616082366, "time_total_s": 16.916001081466675, "pid": 36557, "hostname": "MacBook-Pro-3", "node_ip": "192.168.0.4", "config": {"objective": "binary", "metric": "binary_error", "mode": "max", "verbose": -1, "boosting_type": "dart", "num_leaves": 11, "learning_rate": 0.06681927520553171}, "time_since_restore": 16.916001081466675, "timesteps_since_restore": 0, "iterations_since_restore": 36, "trial_id": "fe4c4_00003"}
{"binary_error": 0.18738475722188075, "time_this_iter_s": 0.11494302749633789, "done": false, "timesteps_total": null, "episodes_total": null, "training_iteration": 37, "experiment_id": "869f30e345a040409cc5f7276756e710", "date": "2021-03-18_15-46-06", "timestamp": 1616082366, "time_total_s": 17.030944108963013, "pid": 36557, "hostname": "MacBook-Pro-3", "node_ip": "192.168.0.4", "config": {"objective": "binary", "metric": "binary_error", "mode": "max", "verbose": -1, "boosting_type": "dart", "num_leaves": 11, "learning_rate": 0.06681927520553171}, "time_since_restore": 17.030944108963013, "timesteps_since_restore": 0, "iterations_since_restore": 37, "trial_id": "fe4c4_00003"}
{"binary_error": 0.18611708666256915, "time_this_iter_s": 0.11753010749816895, "done": false, "timesteps_total": null, "episodes_total": null, "training_iteration": 38, "experiment_id": "869f30e345a040409cc5f7276756e710", "date": "2021-03-18_15-46-06", "timestamp": 1616082366, "time_total_s": 17.14847421646118, "pid": 36557, "hostname": "MacBook-Pro-3", "node_ip": "192.168.0.4", "config": {"objective": "binary", "metric": "binary_error", "mode": "max", "verbose": -1, "boosting_type": "dart", "num_leaves": 11, "learning_rate": 0.06681927520553171}, "time_since_restore": 17.14847421646118, "timesteps_since_restore": 0, "iterations_since_restore": 38, "trial_id": "fe4c4_00003"}
{"binary_error": 0.18496465888137675, "time_this_iter_s": 0.10741996765136719, "done": false, "timesteps_total": null, "episodes_total": null, "training_iteration": 39, "experiment_id": "869f30e345a040409cc5f7276756e710", "date": "2021-03-18_15-46-06", "timestamp": 1616082366, "time_total_s": 17.25589418411255, "pid": 36557, "hostname": "MacBook-Pro-3", "node_ip": "192.168.0.4", "config": {"objective": "binary", "metric": "binary_error", "mode": "max", "verbose": -1, "boosting_type": "dart", "num_leaves": 11, "learning_rate": 0.06681927520553171}, "time_since_restore": 17.25589418411255, "timesteps_since_restore": 0, "iterations_since_restore": 39, "trial_id": "fe4c4_00003"}
{"binary_error": 0.1852719729563614, "time_this_iter_s": 0.13045501708984375, "done": false, "timesteps_total": null, "episodes_total": null, "training_iteration": 40, "experiment_id": "869f30e345a040409cc5f7276756e710", "date": "2021-03-18_15-46-07", "timestamp": 1616082367, "time_total_s": 17.386349201202393, "pid": 36557, "hostname": "MacBook-Pro-3", "node_ip": "192.168.0.4", "config": {"objective": "binary", "metric": "binary_error", "mode": "max", "verbose": -1, "boosting_type": "dart", "num_leaves": 11, "learning_rate": 0.06681927520553171}, "time_since_restore": 17.386349201202393, "timesteps_since_restore": 0, "iterations_since_restore": 40, "trial_id": "fe4c4_00003"}
{"binary_error": 0.186539643515673, "time_this_iter_s": 0.19585204124450684, "done": false, "timesteps_total": null, "episodes_total": null, "training_iteration": 41, "experiment_id": "869f30e345a040409cc5f7276756e710", "date": "2021-03-18_15-46-07", "timestamp": 1616082367, "time_total_s": 17.5822012424469, "pid": 36557, "hostname": "MacBook-Pro-3", "node_ip": "192.168.0.4", "config": {"objective": "binary", "metric": "binary_error", "mode": "max", "verbose": -1, "boosting_type": "dart", "num_leaves": 11, "learning_rate": 0.06681927520553171}, "time_since_restore": 17.5822012424469, "timesteps_since_restore": 0, "iterations_since_restore": 41, "trial_id": "fe4c4_00003"}
{"binary_error": 0.1849262446220037, "time_this_iter_s": 0.12056779861450195, "done": false, "timesteps_total": null, "episodes_total": null, "training_iteration": 42, "experiment_id": "869f30e345a040409cc5f7276756e710", "date": "2021-03-18_15-46-07", "timestamp": 1616082367, "time_total_s": 17.7027690410614, "pid": 36557, "hostname": "MacBook-Pro-3", "node_ip": "192.168.0.4", "config": {"objective": "binary", "metric": "binary_error", "mode": "max", "verbose": -1, "boosting_type": "dart", "num_leaves": 11, "learning_rate": 0.06681927520553171}, "time_since_restore": 17.7027690410614, "timesteps_since_restore": 0, "iterations_since_restore": 42, "trial_id": "fe4c4_00003"}
{"binary_error": 0.186040258143823, "time_this_iter_s": 0.19875025749206543, "done": false, "timesteps_total": null, "episodes_total": null, "training_iteration": 43, "experiment_id": "869f30e345a040409cc5f7276756e710", "date": "2021-03-18_15-46-07", "timestamp": 1616082367, "time_total_s": 17.901519298553467, "pid": 36557, "hostname": "MacBook-Pro-3", "node_ip": "192.168.0.4", "config": {"objective": "binary", "metric": "binary_error", "mode": "max", "verbose": -1, "boosting_type": "dart", "num_leaves": 11, "learning_rate": 0.06681927520553171}, "time_since_restore": 17.901519298553467, "timesteps_since_restore": 0, "iterations_since_restore": 43, "trial_id": "fe4c4_00003"}
{"binary_error": 0.18500307314074985, "time_this_iter_s": 0.11501693725585938, "done": false, "timesteps_total": null, "episodes_total": null, "training_iteration": 44, "experiment_id": "869f30e345a040409cc5f7276756e710", "date": "2021-03-18_15-46-07", "timestamp": 1616082367, "time_total_s": 18.016536235809326, "pid": 36557, "hostname": "MacBook-Pro-3", "node_ip": "192.168.0.4", "config": {"objective": "binary", "metric": "binary_error", "mode": "max", "verbose": -1, "boosting_type": "dart", "num_leaves": 11, "learning_rate": 0.06681927520553171}, "time_since_restore": 18.016536235809326, "timesteps_since_restore": 0, "iterations_since_restore": 44, "trial_id": "fe4c4_00003"}
{"binary_error": 0.18419637369391517, "time_this_iter_s": 0.11767172813415527, "done": false, "timesteps_total": null, "episodes_total": null, "training_iteration": 45, "experiment_id": "869f30e345a040409cc5f7276756e710", "date": "2021-03-18_15-46-07", "timestamp": 1616082367, "time_total_s": 18.13420796394348, "pid": 36557, "hostname": "MacBook-Pro-3", "node_ip": "192.168.0.4", "config": {"objective": "binary", "metric": "binary_error", "mode": "max", "verbose": -1, "boosting_type": "dart", "num_leaves": 11, "learning_rate": 0.06681927520553171}, "time_since_restore": 18.13420796394348, "timesteps_since_restore": 0, "iterations_since_restore": 45, "trial_id": "fe4c4_00003"}
{"binary_error": 0.18035494775660726, "time_this_iter_s": 0.1849651336669922, "done": false, "timesteps_total": null, "episodes_total": null, "training_iteration": 46, "experiment_id": "869f30e345a040409cc5f7276756e710", "date": "2021-03-18_15-46-07", "timestamp": 1616082367, "time_total_s": 18.319173097610474, "pid": 36557, "hostname": "MacBook-Pro-3", "node_ip": "192.168.0.4", "config": {"objective": "binary", "metric": "binary_error", "mode": "max", "verbose": -1, "boosting_type": "dart", "num_leaves": 11, "learning_rate": 0.06681927520553171}, "time_since_restore": 18.319173097610474, "timesteps_since_restore": 0, "iterations_since_restore": 46, "trial_id": "fe4c4_00003"}
{"binary_error": 0.17974031960663797, "time_this_iter_s": 0.12346792221069336, "done": false, "timesteps_total": null, "episodes_total": null, "training_iteration": 47, "experiment_id": "869f30e345a040409cc5f7276756e710", "date": "2021-03-18_15-46-08", "timestamp": 1616082368, "time_total_s": 18.442641019821167, "pid": 36557, "hostname": "MacBook-Pro-3", "node_ip": "192.168.0.4", "config": {"objective": "binary", "metric": "binary_error", "mode": "max", "verbose": -1, "boosting_type": "dart", "num_leaves": 11, "learning_rate": 0.06681927520553171}, "time_since_restore": 18.442641019821167, "timesteps_since_restore": 0, "iterations_since_restore": 47, "trial_id": "fe4c4_00003"}
{"binary_error": 0.18020129071911495, "time_this_iter_s": 0.13574814796447754, "done": false, "timesteps_total": null, "episodes_total": null, "training_iteration": 48, "experiment_id": "869f30e345a040409cc5f7276756e710", "date": "2021-03-18_15-46-08", "timestamp": 1616082368, "time_total_s": 18.578389167785645, "pid": 36557, "hostname": "MacBook-Pro-3", "node_ip": "192.168.0.4", "config": {"objective": "binary", "metric": "binary_error", "mode": "max", "verbose": -1, "boosting_type": "dart", "num_leaves": 11, "learning_rate": 0.06681927520553171}, "time_since_restore": 18.578389167785645, "timesteps_since_restore": 0, "iterations_since_restore": 48, "trial_id": "fe4c4_00003"}
{"binary_error": 0.1806622618315919, "time_this_iter_s": 0.17650985717773438, "done": false, "timesteps_total": null, "episodes_total": null, "training_iteration": 49, "experiment_id": "869f30e345a040409cc5f7276756e710", "date": "2021-03-18_15-46-08", "timestamp": 1616082368, "time_total_s": 18.75489902496338, "pid": 36557, "hostname": "MacBook-Pro-3", "node_ip": "192.168.0.4", "config": {"objective": "binary", "metric": "binary_error", "mode": "max", "verbose": -1, "boosting_type": "dart", "num_leaves": 11, "learning_rate": 0.06681927520553171}, "time_since_restore": 18.75489902496338, "timesteps_since_restore": 0, "iterations_since_restore": 49, "trial_id": "fe4c4_00003"}
{"binary_error": 0.18127688998156116, "time_this_iter_s": 0.16856813430786133, "done": false, "timesteps_total": null, "episodes_total": null, "training_iteration": 50, "experiment_id": "869f30e345a040409cc5f7276756e710", "date": "2021-03-18_15-46-08", "timestamp": 1616082368, "time_total_s": 18.92346715927124, "pid": 36557, "hostname": "MacBook-Pro-3", "node_ip": "192.168.0.4", "config": {"objective": "binary", "metric": "binary_error", "mode": "max", "verbose": -1, "boosting_type": "dart", "num_leaves": 11, "learning_rate": 0.06681927520553171}, "time_since_restore": 18.92346715927124, "timesteps_since_restore": 0, "iterations_since_restore": 50, "trial_id": "fe4c4_00003"}
{"binary_error": 0.1811616472034419, "time_this_iter_s": 0.11120295524597168, "done": false, "timesteps_total": null, "episodes_total": null, "training_iteration": 51, "experiment_id": "869f30e345a040409cc5f7276756e710", "date": "2021-03-18_15-46-08", "timestamp": 1616082368, "time_total_s": 19.034670114517212, "pid": 36557, "hostname": "MacBook-Pro-3", "node_ip": "192.168.0.4", "config": {"objective": "binary", "metric": "binary_error", "mode": "max", "verbose": -1, "boosting_type": "dart", "num_leaves": 11, "learning_rate": 0.06681927520553171}, "time_since_restore": 19.034670114517212, "timesteps_since_restore": 0, "iterations_since_restore": 51, "trial_id": "fe4c4_00003"}
{"binary_error": 0.18089274738783037, "time_this_iter_s": 0.11766600608825684, "done": false, "timesteps_total": null, "episodes_total": null, "training_iteration": 52, "experiment_id": "869f30e345a040409cc5f7276756e710", "date": "2021-03-18_15-46-08", "timestamp": 1616082368, "time_total_s": 19.15233612060547, "pid": 36557, "hostname": "MacBook-Pro-3", "node_ip": "192.168.0.4", "config": {"objective": "binary", "metric": "binary_error", "mode": "max", "verbose": -1, "boosting_type": "dart", "num_leaves": 11, "learning_rate": 0.06681927520553171}, "time_since_restore": 19.15233612060547, "timesteps_since_restore": 0, "iterations_since_restore": 52, "trial_id": "fe4c4_00003"}
{"binary_error": 0.18096957590657653, "time_this_iter_s": 0.16215300559997559, "done": false, "timesteps_total": null, "episodes_total": null, "training_iteration": 53, "experiment_id": "869f30e345a040409cc5f7276756e710", "date": "2021-03-18_15-46-08", "timestamp": 1616082368, "time_total_s": 19.314489126205444, "pid": 36557, "hostname": "MacBook-Pro-3", "node_ip": "192.168.0.4", "config": {"objective": "binary", "metric": "binary_error", "mode": "max", "verbose": -1, "boosting_type": "dart", "num_leaves": 11, "learning_rate": 0.06681927520553171}, "time_since_restore": 19.314489126205444, "timesteps_since_restore": 0, "iterations_since_restore": 53, "trial_id": "fe4c4_00003"}
{"binary_error": 0.1810079901659496, "time_this_iter_s": 0.11737895011901855, "done": false, "timesteps_total": null, "episodes_total": null, "training_iteration": 54, "experiment_id": "869f30e345a040409cc5f7276756e710", "date": "2021-03-18_15-46-09", "timestamp": 1616082369, "time_total_s": 19.431868076324463, "pid": 36557, "hostname": "MacBook-Pro-3", "node_ip": "192.168.0.4", "config": {"objective": "binary", "metric": "binary_error", "mode": "max", "verbose": -1, "boosting_type": "dart", "num_leaves": 11, "learning_rate": 0.06681927520553171}, "time_since_restore": 19.431868076324463, "timesteps_since_restore": 0, "iterations_since_restore": 54, "trial_id": "fe4c4_00003"}
{"binary_error": 0.18077750460971112, "time_this_iter_s": 0.11865401268005371, "done": false, "timesteps_total": null, "episodes_total": null, "training_iteration": 55, "experiment_id": "869f30e345a040409cc5f7276756e710", "date": "2021-03-18_15-46-09", "timestamp": 1616082369, "time_total_s": 19.550522089004517, "pid": 36557, "hostname": "MacBook-Pro-3", "node_ip": "192.168.0.4", "config": {"objective": "binary", "metric": "binary_error", "mode": "max", "verbose": -1, "boosting_type": "dart", "num_leaves": 11, "learning_rate": 0.06681927520553171}, "time_since_restore": 19.550522089004517, "timesteps_since_restore": 0, "iterations_since_restore": 55, "trial_id": "fe4c4_00003"}
{"binary_error": 0.1811616472034419, "time_this_iter_s": 0.20642709732055664, "done": false, "timesteps_total": null, "episodes_total": null, "training_iteration": 56, "experiment_id": "869f30e345a040409cc5f7276756e710", "date": "2021-03-18_15-46-09", "timestamp": 1616082369, "time_total_s": 19.756949186325073, "pid": 36557, "hostname": "MacBook-Pro-3", "node_ip": "192.168.0.4", "config": {"objective": "binary", "metric": "binary_error", "mode": "max", "verbose": -1, "boosting_type": "dart", "num_leaves": 11, "learning_rate": 0.06681927520553171}, "time_since_restore": 19.756949186325073, "timesteps_since_restore": 0, "iterations_since_restore": 56, "trial_id": "fe4c4_00003"}
{"binary_error": 0.18089274738783037, "time_this_iter_s": 0.1255207061767578, "done": false, "timesteps_total": null, "episodes_total": null, "training_iteration": 57, "experiment_id": "869f30e345a040409cc5f7276756e710", "date": "2021-03-18_15-46-09", "timestamp": 1616082369, "time_total_s": 19.88246989250183, "pid": 36557, "hostname": "MacBook-Pro-3", "node_ip": "192.168.0.4", "config": {"objective": "binary", "metric": "binary_error", "mode": "max", "verbose": -1, "boosting_type": "dart", "num_leaves": 11, "learning_rate": 0.06681927520553171}, "time_since_restore": 19.88246989250183, "timesteps_since_restore": 0, "iterations_since_restore": 57, "trial_id": "fe4c4_00003"}
{"binary_error": 0.17751229256299939, "time_this_iter_s": 0.1702721118927002, "done": false, "timesteps_total": null, "episodes_total": null, "training_iteration": 58, "experiment_id": "869f30e345a040409cc5f7276756e710", "date": "2021-03-18_15-46-09", "timestamp": 1616082369, "time_total_s": 20.05274200439453, "pid": 36557, "hostname": "MacBook-Pro-3", "node_ip": "192.168.0.4", "config": {"objective": "binary", "metric": "binary_error", "mode": "max", "verbose": -1, "boosting_type": "dart", "num_leaves": 11, "learning_rate": 0.06681927520553171}, "time_since_restore": 20.05274200439453, "timesteps_since_restore": 0, "iterations_since_restore": 58, "trial_id": "fe4c4_00003"}
{"binary_error": 0.1782421634910879, "time_this_iter_s": 0.19653797149658203, "done": false, "timesteps_total": null, "episodes_total": null, "training_iteration": 59, "experiment_id": "869f30e345a040409cc5f7276756e710", "date": "2021-03-18_15-46-09", "timestamp": 1616082369, "time_total_s": 20.249279975891113, "pid": 36557, "hostname": "MacBook-Pro-3", "node_ip": "192.168.0.4", "config": {"objective": "binary", "metric": "binary_error", "mode": "max", "verbose": -1, "boosting_type": "dart", "num_leaves": 11, "learning_rate": 0.06681927520553171}, "time_since_restore": 20.249279975891113, "timesteps_since_restore": 0, "iterations_since_restore": 59, "trial_id": "fe4c4_00003"}
{"binary_error": 0.17839582052858022, "time_this_iter_s": 0.10836005210876465, "done": false, "timesteps_total": null, "episodes_total": null, "training_iteration": 60, "experiment_id": "869f30e345a040409cc5f7276756e710", "date": "2021-03-18_15-46-09", "timestamp": 1616082369, "time_total_s": 20.357640027999878, "pid": 36557, "hostname": "MacBook-Pro-3", "node_ip": "192.168.0.4", "config": {"objective": "binary", "metric": "binary_error", "mode": "max", "verbose": -1, "boosting_type": "dart", "num_leaves": 11, "learning_rate": 0.06681927520553171}, "time_since_restore": 20.357640027999878, "timesteps_since_restore": 0, "iterations_since_restore": 60, "trial_id": "fe4c4_00003"}
{"binary_error": 0.17693607867240319, "time_this_iter_s": 0.15560102462768555, "done": false, "timesteps_total": null, "episodes_total": null, "training_iteration": 61, "experiment_id": "869f30e345a040409cc5f7276756e710", "date": "2021-03-18_15-46-10", "timestamp": 1616082370, "time_total_s": 20.513241052627563, "pid": 36557, "hostname": "MacBook-Pro-3", "node_ip": "192.168.0.4", "config": {"objective": "binary", "metric": "binary_error", "mode": "max", "verbose": -1, "boosting_type": "dart", "num_leaves": 11, "learning_rate": 0.06681927520553171}, "time_since_restore": 20.513241052627563, "timesteps_since_restore": 0, "iterations_since_restore": 61, "trial_id": "fe4c4_00003"}
{"binary_error": 0.17701290719114934, "time_this_iter_s": 0.10932016372680664, "done": false, "timesteps_total": null, "episodes_total": null, "training_iteration": 62, "experiment_id": "869f30e345a040409cc5f7276756e710", "date": "2021-03-18_15-46-10", "timestamp": 1616082370, "time_total_s": 20.62256121635437, "pid": 36557, "hostname": "MacBook-Pro-3", "node_ip": "192.168.0.4", "config": {"objective": "binary", "metric": "binary_error", "mode": "max", "verbose": -1, "boosting_type": "dart", "num_leaves": 11, "learning_rate": 0.06681927520553171}, "time_since_restore": 20.62256121635437, "timesteps_since_restore": 0, "iterations_since_restore": 62, "trial_id": "fe4c4_00003"}
{"binary_error": 0.17724339274738782, "time_this_iter_s": 0.11048173904418945, "done": false, "timesteps_total": null, "episodes_total": null, "training_iteration": 63, "experiment_id": "869f30e345a040409cc5f7276756e710", "date": "2021-03-18_15-46-10", "timestamp": 1616082370, "time_total_s": 20.73304295539856, "pid": 36557, "hostname": "MacBook-Pro-3", "node_ip": "192.168.0.4", "config": {"objective": "binary", "metric": "binary_error", "mode": "max", "verbose": -1, "boosting_type": "dart", "num_leaves": 11, "learning_rate": 0.06681927520553171}, "time_since_restore": 20.73304295539856, "timesteps_since_restore": 0, "iterations_since_restore": 63, "trial_id": "fe4c4_00003"}
{"binary_error": 0.17682083589428396, "time_this_iter_s": 0.1679821014404297, "done": false, "timesteps_total": null, "episodes_total": null, "training_iteration": 64, "experiment_id": "869f30e345a040409cc5f7276756e710", "date": "2021-03-18_15-46-10", "timestamp": 1616082370, "time_total_s": 20.90102505683899, "pid": 36557, "hostname": "MacBook-Pro-3", "node_ip": "192.168.0.4", "config": {"objective": "binary", "metric": "binary_error", "mode": "max", "verbose": -1, "boosting_type": "dart", "num_leaves": 11, "learning_rate": 0.06681927520553171}, "time_since_restore": 20.90102505683899, "timesteps_since_restore": 0, "iterations_since_restore": 64, "trial_id": "fe4c4_00003"}
{"binary_error": 0.17666717885679165, "time_this_iter_s": 0.2153301239013672, "done": false, "timesteps_total": null, "episodes_total": null, "training_iteration": 65, "experiment_id": "869f30e345a040409cc5f7276756e710", "date": "2021-03-18_15-46-10", "timestamp": 1616082370, "time_total_s": 21.116355180740356, "pid": 36557, "hostname": "MacBook-Pro-3", "node_ip": "192.168.0.4", "config": {"objective": "binary", "metric": "binary_error", "mode": "max", "verbose": -1, "boosting_type": "dart", "num_leaves": 11, "learning_rate": 0.06681927520553171}, "time_since_restore": 21.116355180740356, "timesteps_since_restore": 0, "iterations_since_restore": 65, "trial_id": "fe4c4_00003"}
{"binary_error": 0.17689766441303012, "time_this_iter_s": 0.10522174835205078, "done": false, "timesteps_total": null, "episodes_total": null, "training_iteration": 66, "experiment_id": "869f30e345a040409cc5f7276756e710", "date": "2021-03-18_15-46-10", "timestamp": 1616082370, "time_total_s": 21.221576929092407, "pid": 36557, "hostname": "MacBook-Pro-3", "node_ip": "192.168.0.4", "config": {"objective": "binary", "metric": "binary_error", "mode": "max", "verbose": -1, "boosting_type": "dart", "num_leaves": 11, "learning_rate": 0.06681927520553171}, "time_since_restore": 21.221576929092407, "timesteps_since_restore": 0, "iterations_since_restore": 66, "trial_id": "fe4c4_00003"}
{"binary_error": 0.17689766441303012, "time_this_iter_s": 0.11174726486206055, "done": false, "timesteps_total": null, "episodes_total": null, "training_iteration": 67, "experiment_id": "869f30e345a040409cc5f7276756e710", "date": "2021-03-18_15-46-10", "timestamp": 1616082370, "time_total_s": 21.333324193954468, "pid": 36557, "hostname": "MacBook-Pro-3", "node_ip": "192.168.0.4", "config": {"objective": "binary", "metric": "binary_error", "mode": "max", "verbose": -1, "boosting_type": "dart", "num_leaves": 11, "learning_rate": 0.06681927520553171}, "time_since_restore": 21.333324193954468, "timesteps_since_restore": 0, "iterations_since_restore": 67, "trial_id": "fe4c4_00003"}
{"binary_error": 0.17697449293177628, "time_this_iter_s": 0.1111459732055664, "done": false, "timesteps_total": null, "episodes_total": null, "training_iteration": 68, "experiment_id": "869f30e345a040409cc5f7276756e710", "date": "2021-03-18_15-46-11", "timestamp": 1616082371, "time_total_s": 21.444470167160034, "pid": 36557, "hostname": "MacBook-Pro-3", "node_ip": "192.168.0.4", "config": {"objective": "binary", "metric": "binary_error", "mode": "max", "verbose": -1, "boosting_type": "dart", "num_leaves": 11, "learning_rate": 0.06681927520553171}, "time_since_restore": 21.444470167160034, "timesteps_since_restore": 0, "iterations_since_restore": 68, "trial_id": "fe4c4_00003"}
{"binary_error": 0.17743546404425323, "time_this_iter_s": 0.1803297996520996, "done": false, "timesteps_total": null, "episodes_total": null, "training_iteration": 69, "experiment_id": "869f30e345a040409cc5f7276756e710", "date": "2021-03-18_15-46-11", "timestamp": 1616082371, "time_total_s": 21.624799966812134, "pid": 36557, "hostname": "MacBook-Pro-3", "node_ip": "192.168.0.4", "config": {"objective": "binary", "metric": "binary_error", "mode": "max", "verbose": -1, "boosting_type": "dart", "num_leaves": 11, "learning_rate": 0.06681927520553171}, "time_since_restore": 21.624799966812134, "timesteps_since_restore": 0, "iterations_since_restore": 69, "trial_id": "fe4c4_00003"}
{"binary_error": 0.17735863552550707, "time_this_iter_s": 0.18287420272827148, "done": false, "timesteps_total": null, "episodes_total": null, "training_iteration": 70, "experiment_id": "869f30e345a040409cc5f7276756e710", "date": "2021-03-18_15-46-11", "timestamp": 1616082371, "time_total_s": 21.807674169540405, "pid": 36557, "hostname": "MacBook-Pro-3", "node_ip": "192.168.0.4", "config": {"objective": "binary", "metric": "binary_error", "mode": "max", "verbose": -1, "boosting_type": "dart", "num_leaves": 11, "learning_rate": 0.06681927520553171}, "time_since_restore": 21.807674169540405, "timesteps_since_restore": 0, "iterations_since_restore": 70, "trial_id": "fe4c4_00003"}
{"binary_error": 0.17774277811923786, "time_this_iter_s": 0.15401601791381836, "done": false, "timesteps_total": null, "episodes_total": null, "training_iteration": 71, "experiment_id": "869f30e345a040409cc5f7276756e710", "date": "2021-03-18_15-46-11", "timestamp": 1616082371, "time_total_s": 21.961690187454224, "pid": 36557, "hostname": "MacBook-Pro-3", "node_ip": "192.168.0.4", "config": {"objective": "binary", "metric": "binary_error", "mode": "max", "verbose": -1, "boosting_type": "dart", "num_leaves": 11, "learning_rate": 0.06681927520553171}, "time_since_restore": 21.961690187454224, "timesteps_since_restore": 0, "iterations_since_restore": 71, "trial_id": "fe4c4_00003"}
{"binary_error": 0.17797326367547633, "time_this_iter_s": 0.11021804809570312, "done": false, "timesteps_total": null, "episodes_total": null, "training_iteration": 72, "experiment_id": "869f30e345a040409cc5f7276756e710", "date": "2021-03-18_15-46-11", "timestamp": 1616082371, "time_total_s": 22.071908235549927, "pid": 36557, "hostname": "MacBook-Pro-3", "node_ip": "192.168.0.4", "config": {"objective": "binary", "metric": "binary_error", "mode": "max", "verbose": -1, "boosting_type": "dart", "num_leaves": 11, "learning_rate": 0.06681927520553171}, "time_since_restore": 22.071908235549927, "timesteps_since_restore": 0, "iterations_since_restore": 72, "trial_id": "fe4c4_00003"}
{"binary_error": 0.1782421634910879, "time_this_iter_s": 0.11617469787597656, "done": false, "timesteps_total": null, "episodes_total": null, "training_iteration": 73, "experiment_id": "869f30e345a040409cc5f7276756e710", "date": "2021-03-18_15-46-11", "timestamp": 1616082371, "time_total_s": 22.188082933425903, "pid": 36557, "hostname": "MacBook-Pro-3", "node_ip": "192.168.0.4", "config": {"objective": "binary", "metric": "binary_error", "mode": "max", "verbose": -1, "boosting_type": "dart", "num_leaves": 11, "learning_rate": 0.06681927520553171}, "time_since_restore": 22.188082933425903, "timesteps_since_restore": 0, "iterations_since_restore": 73, "trial_id": "fe4c4_00003"}
{"binary_error": 0.17839582052858022, "time_this_iter_s": 0.21833014488220215, "done": false, "timesteps_total": null, "episodes_total": null, "training_iteration": 74, "experiment_id": "869f30e345a040409cc5f7276756e710", "date": "2021-03-18_15-46-12", "timestamp": 1616082372, "time_total_s": 22.406413078308105, "pid": 36557, "hostname": "MacBook-Pro-3", "node_ip": "192.168.0.4", "config": {"objective": "binary", "metric": "binary_error", "mode": "max", "verbose": -1, "boosting_type": "dart", "num_leaves": 11, "learning_rate": 0.06681927520553171}, "time_since_restore": 22.406413078308105, "timesteps_since_restore": 0, "iterations_since_restore": 74, "trial_id": "fe4c4_00003"}
{"binary_error": 0.1780500921942225, "time_this_iter_s": 0.11877799034118652, "done": false, "timesteps_total": null, "episodes_total": null, "training_iteration": 75, "experiment_id": "869f30e345a040409cc5f7276756e710", "date": "2021-03-18_15-46-12", "timestamp": 1616082372, "time_total_s": 22.525191068649292, "pid": 36557, "hostname": "MacBook-Pro-3", "node_ip": "192.168.0.4", "config": {"objective": "binary", "metric": "binary_error", "mode": "max", "verbose": -1, "boosting_type": "dart", "num_leaves": 11, "learning_rate": 0.06681927520553171}, "time_since_restore": 22.525191068649292, "timesteps_since_restore": 0, "iterations_since_restore": 75, "trial_id": "fe4c4_00003"}
{"binary_error": 0.1782037492317148, "time_this_iter_s": 0.1464519500732422, "done": false, "timesteps_total": null, "episodes_total": null, "training_iteration": 76, "experiment_id": "869f30e345a040409cc5f7276756e710", "date": "2021-03-18_15-46-12", "timestamp": 1616082372, "time_total_s": 22.671643018722534, "pid": 36557, "hostname": "MacBook-Pro-3", "node_ip": "192.168.0.4", "config": {"objective": "binary", "metric": "binary_error", "mode": "max", "verbose": -1, "boosting_type": "dart", "num_leaves": 11, "learning_rate": 0.06681927520553171}, "time_since_restore": 22.671643018722534, "timesteps_since_restore": 0, "iterations_since_restore": 76, "trial_id": "fe4c4_00003"}
{"binary_error": 0.17839582052858022, "time_this_iter_s": 0.2259061336517334, "done": false, "timesteps_total": null, "episodes_total": null, "training_iteration": 77, "experiment_id": "869f30e345a040409cc5f7276756e710", "date": "2021-03-18_15-46-12", "timestamp": 1616082372, "time_total_s": 22.897549152374268, "pid": 36557, "hostname": "MacBook-Pro-3", "node_ip": "192.168.0.4", "config": {"objective": "binary", "metric": "binary_error", "mode": "max", "verbose": -1, "boosting_type": "dart", "num_leaves": 11, "learning_rate": 0.06681927520553171}, "time_since_restore": 22.897549152374268, "timesteps_since_restore": 0, "iterations_since_restore": 77, "trial_id": "fe4c4_00003"}
{"binary_error": 0.17870313460356485, "time_this_iter_s": 0.19132685661315918, "done": false, "timesteps_total": null, "episodes_total": null, "training_iteration": 78, "experiment_id": "869f30e345a040409cc5f7276756e710", "date": "2021-03-18_15-46-12", "timestamp": 1616082372, "time_total_s": 23.088876008987427, "pid": 36557, "hostname": "MacBook-Pro-3", "node_ip": "192.168.0.4", "config": {"objective": "binary", "metric": "binary_error", "mode": "max", "verbose": -1, "boosting_type": "dart", "num_leaves": 11, "learning_rate": 0.06681927520553171}, "time_since_restore": 23.088876008987427, "timesteps_since_restore": 0, "iterations_since_restore": 78, "trial_id": "fe4c4_00003"}
{"binary_error": 0.17866472034419176, "time_this_iter_s": 0.10869908332824707, "done": false, "timesteps_total": null, "episodes_total": null, "training_iteration": 79, "experiment_id": "869f30e345a040409cc5f7276756e710", "date": "2021-03-18_15-46-12", "timestamp": 1616082372, "time_total_s": 23.197575092315674, "pid": 36557, "hostname": "MacBook-Pro-3", "node_ip": "192.168.0.4", "config": {"objective": "binary", "metric": "binary_error", "mode": "max", "verbose": -1, "boosting_type": "dart", "num_leaves": 11, "learning_rate": 0.06681927520553171}, "time_since_restore": 23.197575092315674, "timesteps_since_restore": 0, "iterations_since_restore": 79, "trial_id": "fe4c4_00003"}
{"binary_error": 0.17843423478795328, "time_this_iter_s": 0.11910200119018555, "done": false, "timesteps_total": null, "episodes_total": null, "training_iteration": 80, "experiment_id": "869f30e345a040409cc5f7276756e710", "date": "2021-03-18_15-46-12", "timestamp": 1616082372, "time_total_s": 23.31667709350586, "pid": 36557, "hostname": "MacBook-Pro-3", "node_ip": "192.168.0.4", "config": {"objective": "binary", "metric": "binary_error", "mode": "max", "verbose": -1, "boosting_type": "dart", "num_leaves": 11, "learning_rate": 0.06681927520553171}, "time_since_restore": 23.31667709350586, "timesteps_since_restore": 0, "iterations_since_restore": 80, "trial_id": "fe4c4_00003"}
{"binary_error": 0.17870313460356485, "time_this_iter_s": 0.19514799118041992, "done": false, "timesteps_total": null, "episodes_total": null, "training_iteration": 81, "experiment_id": "869f30e345a040409cc5f7276756e710", "date": "2021-03-18_15-46-13", "timestamp": 1616082373, "time_total_s": 23.51182508468628, "pid": 36557, "hostname": "MacBook-Pro-3", "node_ip": "192.168.0.4", "config": {"objective": "binary", "metric": "binary_error", "mode": "max", "verbose": -1, "boosting_type": "dart", "num_leaves": 11, "learning_rate": 0.06681927520553171}, "time_since_restore": 23.51182508468628, "timesteps_since_restore": 0, "iterations_since_restore": 81, "trial_id": "fe4c4_00003"}
{"binary_error": 0.17851106330669944, "time_this_iter_s": 0.10975098609924316, "done": false, "timesteps_total": null, "episodes_total": null, "training_iteration": 82, "experiment_id": "869f30e345a040409cc5f7276756e710", "date": "2021-03-18_15-46-13", "timestamp": 1616082373, "time_total_s": 23.621576070785522, "pid": 36557, "hostname": "MacBook-Pro-3", "node_ip": "192.168.0.4", "config": {"objective": "binary", "metric": "binary_error", "mode": "max", "verbose": -1, "boosting_type": "dart", "num_leaves": 11, "learning_rate": 0.06681927520553171}, "time_since_restore": 23.621576070785522, "timesteps_since_restore": 0, "iterations_since_restore": 82, "trial_id": "fe4c4_00003"}
{"binary_error": 0.17843423478795328, "time_this_iter_s": 0.18879294395446777, "done": false, "timesteps_total": null, "episodes_total": null, "training_iteration": 83, "experiment_id": "869f30e345a040409cc5f7276756e710", "date": "2021-03-18_15-46-13", "timestamp": 1616082373, "time_total_s": 23.81036901473999, "pid": 36557, "hostname": "MacBook-Pro-3", "node_ip": "192.168.0.4", "config": {"objective": "binary", "metric": "binary_error", "mode": "max", "verbose": -1, "boosting_type": "dart", "num_leaves": 11, "learning_rate": 0.06681927520553171}, "time_since_restore": 23.81036901473999, "timesteps_since_restore": 0, "iterations_since_restore": 83, "trial_id": "fe4c4_00003"}
{"binary_error": 0.1786263060848187, "time_this_iter_s": 0.17514610290527344, "done": false, "timesteps_total": null, "episodes_total": null, "training_iteration": 84, "experiment_id": "869f30e345a040409cc5f7276756e710", "date": "2021-03-18_15-46-13", "timestamp": 1616082373, "time_total_s": 23.985515117645264, "pid": 36557, "hostname": "MacBook-Pro-3", "node_ip": "192.168.0.4", "config": {"objective": "binary", "metric": "binary_error", "mode": "max", "verbose": -1, "boosting_type": "dart", "num_leaves": 11, "learning_rate": 0.06681927520553171}, "time_since_restore": 23.985515117645264, "timesteps_since_restore": 0, "iterations_since_restore": 84, "trial_id": "fe4c4_00003"}
{"binary_error": 0.1785878918254456, "time_this_iter_s": 0.33231306076049805, "done": false, "timesteps_total": null, "episodes_total": null, "training_iteration": 85, "experiment_id": "869f30e345a040409cc5f7276756e710", "date": "2021-03-18_15-46-13", "timestamp": 1616082373, "time_total_s": 24.31782817840576, "pid": 36557, "hostname": "MacBook-Pro-3", "node_ip": "192.168.0.4", "config": {"objective": "binary", "metric": "binary_error", "mode": "max", "verbose": -1, "boosting_type": "dart", "num_leaves": 11, "learning_rate": 0.06681927520553171}, "time_since_restore": 24.31782817840576, "timesteps_since_restore": 0, "iterations_since_restore": 85, "trial_id": "fe4c4_00003"}
{"binary_error": 0.17843423478795328, "time_this_iter_s": 0.10552287101745605, "done": false, "timesteps_total": null, "episodes_total": null, "training_iteration": 86, "experiment_id": "869f30e345a040409cc5f7276756e710", "date": "2021-03-18_15-46-14", "timestamp": 1616082374, "time_total_s": 24.423351049423218, "pid": 36557, "hostname": "MacBook-Pro-3", "node_ip": "192.168.0.4", "config": {"objective": "binary", "metric": "binary_error", "mode": "max", "verbose": -1, "boosting_type": "dart", "num_leaves": 11, "learning_rate": 0.06681927520553171}, "time_since_restore": 24.423351049423218, "timesteps_since_restore": 0, "iterations_since_restore": 86, "trial_id": "fe4c4_00003"}
{"binary_error": 0.1780500921942225, "time_this_iter_s": 0.09482598304748535, "done": false, "timesteps_total": null, "episodes_total": null, "training_iteration": 87, "experiment_id": "869f30e345a040409cc5f7276756e710", "date": "2021-03-18_15-46-14", "timestamp": 1616082374, "time_total_s": 24.518177032470703, "pid": 36557, "hostname": "MacBook-Pro-3", "node_ip": "192.168.0.4", "config": {"objective": "binary", "metric": "binary_error", "mode": "max", "verbose": -1, "boosting_type": "dart", "num_leaves": 11, "learning_rate": 0.06681927520553171}, "time_since_restore": 24.518177032470703, "timesteps_since_restore": 0, "iterations_since_restore": 87, "trial_id": "fe4c4_00003"}
{"binary_error": 0.17828057775046097, "time_this_iter_s": 0.23873519897460938, "done": false, "timesteps_total": null, "episodes_total": null, "training_iteration": 88, "experiment_id": "869f30e345a040409cc5f7276756e710", "date": "2021-03-18_15-46-14", "timestamp": 1616082374, "time_total_s": 24.756912231445312, "pid": 36557, "hostname": "MacBook-Pro-3", "node_ip": "192.168.0.4", "config": {"objective": "binary", "metric": "binary_error", "mode": "max", "verbose": -1, "boosting_type": "dart", "num_leaves": 11, "learning_rate": 0.06681927520553171}, "time_since_restore": 24.756912231445312, "timesteps_since_restore": 0, "iterations_since_restore": 88, "trial_id": "fe4c4_00003"}
{"binary_error": 0.1789720344191764, "time_this_iter_s": 0.19663596153259277, "done": false, "timesteps_total": null, "episodes_total": null, "training_iteration": 89, "experiment_id": "869f30e345a040409cc5f7276756e710", "date": "2021-03-18_15-46-14", "timestamp": 1616082374, "time_total_s": 24.953548192977905, "pid": 36557, "hostname": "MacBook-Pro-3", "node_ip": "192.168.0.4", "config": {"objective": "binary", "metric": "binary_error", "mode": "max", "verbose": -1, "boosting_type": "dart", "num_leaves": 11, "learning_rate": 0.06681927520553171}, "time_since_restore": 24.953548192977905, "timesteps_since_restore": 0, "iterations_since_restore": 89, "trial_id": "fe4c4_00003"}
{"binary_error": 0.17920251997541486, "time_this_iter_s": 0.21567487716674805, "done": false, "timesteps_total": null, "episodes_total": null, "training_iteration": 90, "experiment_id": "869f30e345a040409cc5f7276756e710", "date": "2021-03-18_15-46-14", "timestamp": 1616082374, "time_total_s": 25.169223070144653, "pid": 36557, "hostname": "MacBook-Pro-3", "node_ip": "192.168.0.4", "config": {"objective": "binary", "metric": "binary_error", "mode": "max", "verbose": -1, "boosting_type": "dart", "num_leaves": 11, "learning_rate": 0.06681927520553171}, "time_since_restore": 25.169223070144653, "timesteps_since_restore": 0, "iterations_since_restore": 90, "trial_id": "fe4c4_00003"}
{"binary_error": 0.17705132145052244, "time_this_iter_s": 0.15753602981567383, "done": false, "timesteps_total": null, "episodes_total": null, "training_iteration": 91, "experiment_id": "869f30e345a040409cc5f7276756e710", "date": "2021-03-18_15-46-14", "timestamp": 1616082374, "time_total_s": 25.326759099960327, "pid": 36557, "hostname": "MacBook-Pro-3", "node_ip": "192.168.0.4", "config": {"objective": "binary", "metric": "binary_error", "mode": "max", "verbose": -1, "boosting_type": "dart", "num_leaves": 11, "learning_rate": 0.06681927520553171}, "time_since_restore": 25.326759099960327, "timesteps_since_restore": 0, "iterations_since_restore": 91, "trial_id": "fe4c4_00003"}
{"binary_error": 0.17758912108174554, "time_this_iter_s": 0.09781599044799805, "done": false, "timesteps_total": null, "episodes_total": null, "training_iteration": 92, "experiment_id": "869f30e345a040409cc5f7276756e710", "date": "2021-03-18_15-46-15", "timestamp": 1616082375, "time_total_s": 25.424575090408325, "pid": 36557, "hostname": "MacBook-Pro-3", "node_ip": "192.168.0.4", "config": {"objective": "binary", "metric": "binary_error", "mode": "max", "verbose": -1, "boosting_type": "dart", "num_leaves": 11, "learning_rate": 0.06681927520553171}, "time_since_restore": 25.424575090408325, "timesteps_since_restore": 0, "iterations_since_restore": 92, "trial_id": "fe4c4_00003"}
{"binary_error": 0.1780500921942225, "time_this_iter_s": 0.10556483268737793, "done": false, "timesteps_total": null, "episodes_total": null, "training_iteration": 93, "experiment_id": "869f30e345a040409cc5f7276756e710", "date": "2021-03-18_15-46-15", "timestamp": 1616082375, "time_total_s": 25.530139923095703, "pid": 36557, "hostname": "MacBook-Pro-3", "node_ip": "192.168.0.4", "config": {"objective": "binary", "metric": "binary_error", "mode": "max", "verbose": -1, "boosting_type": "dart", "num_leaves": 11, "learning_rate": 0.06681927520553171}, "time_since_restore": 25.530139923095703, "timesteps_since_restore": 0, "iterations_since_restore": 93, "trial_id": "fe4c4_00003"}
{"binary_error": 0.17793484941610327, "time_this_iter_s": 0.18833518028259277, "done": false, "timesteps_total": null, "episodes_total": null, "training_iteration": 94, "experiment_id": "869f30e345a040409cc5f7276756e710", "date": "2021-03-18_15-46-15", "timestamp": 1616082375, "time_total_s": 25.718475103378296, "pid": 36557, "hostname": "MacBook-Pro-3", "node_ip": "192.168.0.4", "config": {"objective": "binary", "metric": "binary_error", "mode": "max", "verbose": -1, "boosting_type": "dart", "num_leaves": 11, "learning_rate": 0.06681927520553171}, "time_since_restore": 25.718475103378296, "timesteps_since_restore": 0, "iterations_since_restore": 94, "trial_id": "fe4c4_00003"}
{"binary_error": 0.1777043638598648, "time_this_iter_s": 0.22757601737976074, "done": false, "timesteps_total": null, "episodes_total": null, "training_iteration": 95, "experiment_id": "869f30e345a040409cc5f7276756e710", "date": "2021-03-18_15-46-15", "timestamp": 1616082375, "time_total_s": 25.946051120758057, "pid": 36557, "hostname": "MacBook-Pro-3", "node_ip": "192.168.0.4", "config": {"objective": "binary", "metric": "binary_error", "mode": "max", "verbose": -1, "boosting_type": "dart", "num_leaves": 11, "learning_rate": 0.06681927520553171}, "time_since_restore": 25.946051120758057, "timesteps_since_restore": 0, "iterations_since_restore": 95, "trial_id": "fe4c4_00003"}
{"binary_error": 0.17778119237861095, "time_this_iter_s": 0.21016502380371094, "done": false, "timesteps_total": null, "episodes_total": null, "training_iteration": 96, "experiment_id": "869f30e345a040409cc5f7276756e710", "date": "2021-03-18_15-46-15", "timestamp": 1616082375, "time_total_s": 26.156216144561768, "pid": 36557, "hostname": "MacBook-Pro-3", "node_ip": "192.168.0.4", "config": {"objective": "binary", "metric": "binary_error", "mode": "max", "verbose": -1, "boosting_type": "dart", "num_leaves": 11, "learning_rate": 0.06681927520553171}, "time_since_restore": 26.156216144561768, "timesteps_since_restore": 0, "iterations_since_restore": 96, "trial_id": "fe4c4_00003"}
{"binary_error": 0.17774277811923786, "time_this_iter_s": 0.09944891929626465, "done": false, "timesteps_total": null, "episodes_total": null, "training_iteration": 97, "experiment_id": "869f30e345a040409cc5f7276756e710", "date": "2021-03-18_15-46-15", "timestamp": 1616082375, "time_total_s": 26.255665063858032, "pid": 36557, "hostname": "MacBook-Pro-3", "node_ip": "192.168.0.4", "config": {"objective": "binary", "metric": "binary_error", "mode": "max", "verbose": -1, "boosting_type": "dart", "num_leaves": 11, "learning_rate": 0.06681927520553171}, "time_since_restore": 26.255665063858032, "timesteps_since_restore": 0, "iterations_since_restore": 97, "trial_id": "fe4c4_00003"}
{"binary_error": 0.17797326367547633, "time_this_iter_s": 0.19652485847473145, "done": false, "timesteps_total": null, "episodes_total": null, "training_iteration": 98, "experiment_id": "869f30e345a040409cc5f7276756e710", "date": "2021-03-18_15-46-16", "timestamp": 1616082376, "time_total_s": 26.452189922332764, "pid": 36557, "hostname": "MacBook-Pro-3", "node_ip": "192.168.0.4", "config": {"objective": "binary", "metric": "binary_error", "mode": "max", "verbose": -1, "boosting_type": "dart", "num_leaves": 11, "learning_rate": 0.06681927520553171}, "time_since_restore": 26.452189922332764, "timesteps_since_restore": 0, "iterations_since_restore": 98, "trial_id": "fe4c4_00003"}
{"binary_error": 0.17797326367547633, "time_this_iter_s": 0.10689210891723633, "done": false, "timesteps_total": null, "episodes_total": null, "training_iteration": 99, "experiment_id": "869f30e345a040409cc5f7276756e710", "date": "2021-03-18_15-46-16", "timestamp": 1616082376, "time_total_s": 26.55908203125, "pid": 36557, "hostname": "MacBook-Pro-3", "node_ip": "192.168.0.4", "config": {"objective": "binary", "metric": "binary_error", "mode": "max", "verbose": -1, "boosting_type": "dart", "num_leaves": 11, "learning_rate": 0.06681927520553171}, "time_since_restore": 26.55908203125, "timesteps_since_restore": 0, "iterations_since_restore": 99, "trial_id": "fe4c4_00003"}
{"binary_error": 0.1777043638598648, "time_this_iter_s": 0.10708212852478027, "done": false, "timesteps_total": null, "episodes_total": null, "training_iteration": 100, "experiment_id": "869f30e345a040409cc5f7276756e710", "date": "2021-03-18_15-46-16", "timestamp": 1616082376, "time_total_s": 26.66616415977478, "pid": 36557, "hostname": "MacBook-Pro-3", "node_ip": "192.168.0.4", "config": {"objective": "binary", "metric": "binary_error", "mode": "max", "verbose": -1, "boosting_type": "dart", "num_leaves": 11, "learning_rate": 0.06681927520553171}, "time_since_restore": 26.66616415977478, "timesteps_since_restore": 0, "iterations_since_restore": 100, "trial_id": "fe4c4_00003"}
{"binary_error": 0.6679769030298165, "done": true, "time_this_iter_s": 1.0525588989257812, "timesteps_total": null, "episodes_total": null, "training_iteration": 101, "experiment_id": "869f30e345a040409cc5f7276756e710", "date": "2021-03-18_15-46-17", "timestamp": 1616082377, "time_total_s": 27.71872305870056, "pid": 36557, "hostname": "MacBook-Pro-3", "node_ip": "192.168.0.4", "config": {"objective": "binary", "metric": "binary_error", "mode": "max", "verbose": -1, "boosting_type": "dart", "num_leaves": 11, "learning_rate": 0.06681927520553171}, "time_since_restore": 27.71872305870056, "timesteps_since_restore": 0, "iterations_since_restore": 101, "trial_id": "fe4c4_00003"}
